odoo/addons/purchase_request_exception/README.rst
odoo/addons/purchase_request_exception/__init__.py
odoo/addons/purchase_request_exception/__manifest__.py
odoo/addons/purchase_request_exception/data/purchase_request_exception_data.xml
odoo/addons/purchase_request_exception/i18n/es.po
odoo/addons/purchase_request_exception/i18n/fr.po
odoo/addons/purchase_request_exception/i18n/it.po
odoo/addons/purchase_request_exception/i18n/purchase_request_exception.pot
odoo/addons/purchase_request_exception/models/__init__.py
odoo/addons/purchase_request_exception/models/exception_rule.py
odoo/addons/purchase_request_exception/models/purchase_request.py
odoo/addons/purchase_request_exception/models/purchase_request_line.py
odoo/addons/purchase_request_exception/readme/CONTRIBUTORS.rst
odoo/addons/purchase_request_exception/readme/DESCRIPTION.rst
odoo/addons/purchase_request_exception/security/ir.model.access.csv
odoo/addons/purchase_request_exception/static/description/icon.png
odoo/addons/purchase_request_exception/static/description/index.html
odoo/addons/purchase_request_exception/tests/__init__.py
odoo/addons/purchase_request_exception/tests/test_purchase_request_exception.py
odoo/addons/purchase_request_exception/views/purchase_request_view.xml
odoo/addons/purchase_request_exception/wizard/__init__.py
odoo/addons/purchase_request_exception/wizard/purchase_request_exception_confirm.py
odoo/addons/purchase_request_exception/wizard/purchase_request_exception_confirm_view.xml
odoo14_addon_purchase_request_exception-14.0.1.0.1.dev10.dist-info/METADATA
odoo14_addon_purchase_request_exception-14.0.1.0.1.dev10.dist-info/WHEEL
odoo14_addon_purchase_request_exception-14.0.1.0.1.dev10.dist-info/top_level.txt
odoo14_addon_purchase_request_exception-14.0.1.0.1.dev10.dist-info/RECORD
