Metadata-Version: 2.1
Name: odoo14-addon-purchase_request_exception
Version: 14.0.1.0.1.dev10
Summary: Custom exceptions on purchase request
Home-page: https://github.com/OCA/purchase-workflow
Author: Ecosoft, Odoo Community Association (OCA)
Author-email: support@odoo-community.org
License: AGPL-3
Classifier: Programming Language :: Python
Classifier: Framework :: Odoo
Classifier: Framework :: Odoo :: 14.0
Classifier: License :: OSI Approved :: GNU Affero General Public License v3
Requires-Python: >=3.6
Requires-Dist: odoo14-addon-base-exception
Requires-Dist: odoo14-addon-purchase-request
Requires-Dist: odoo<14.1dev,>=14.0a
